my_mu3/__init__.py
my_mu3/mu3_image_grabber.py
my_mu3/setup_wlan.py
my_mu3-0.0.3.dist-info/LICENSE
my_mu3-0.0.3.dist-info/METADATA
my_mu3-0.0.3.dist-info/WHEEL
my_mu3-0.0.3.dist-info/entry_points.txt
my_mu3-0.0.3.dist-info/top_level.txt
my_mu3-0.0.3.dist-info/RECORD
