Metadata-Version: 2.1
Name: my-mu3
Version: 0.0.3
Summary: A small project to grab and parse images from the MU3 Vision Sensor.
Author-email: MZandtheRaspberryPi <mzandtheraspberrypi@gmail.com>
Project-URL: Homepage, https://github.com/MZandtheRaspberryPi/my_mu3
Classifier: Programming Language :: Python :: 3
Classifier: License :: OSI Approved :: MIT License
Classifier: Operating System :: OS Independent
Requires-Python: >=3.6
License-File: LICENSE
Requires-Dist: pyserial
Requires-Dist: opencv-python
